.DS_Store
src/__init__.py
src/xcai.py
xcai/__init__.py
xcai/xcai.py
xcai-0.2.1.dist-info/LICENSE
xcai-0.2.1.dist-info/METADATA
xcai-0.2.1.dist-info/WHEEL
xcai-0.2.1.dist-info/top_level.txt
xcai-0.2.1.dist-info/RECORD
