Metadata-Version: 2.1
Name: xcai
Version: 0.2.1
Summary: We make AI simple for you
Author: XiaoChuang.ai
Author-email: sup@XiaoChuangai.com
License: MIT
Keywords: ai AI simple
Classifier: Development Status :: 3 - Alpha
Classifier: Intended Audience :: Developers
Classifier: Natural Language :: English
Classifier: Programming Language :: Python :: 3
Classifier: Programming Language :: Python :: 3.7
Classifier: Programming Language :: Python :: 3.8
Classifier: Programming Language :: Python :: 3.9
Classifier: Programming Language :: Python :: 3.10
Classifier: Programming Language :: Python :: 3.11
Classifier: Programming Language :: Python :: 3.12
Classifier: License :: OSI Approved :: MIT License
License-File: LICENSE
Requires-Dist: requests
